QuantumPathQSOAPySDK/QSOAPlatform.py
QuantumPathQSOAPySDK/__init__.py
QuantumPathQSOAPySDK/circuit/__init__.py
QuantumPathQSOAPySDK/circuit/annealing/CircuitAnnealing.py
QuantumPathQSOAPySDK/circuit/annealing/__init__.py
QuantumPathQSOAPySDK/circuit/annealing/components.py
QuantumPathQSOAPySDK/circuit/flow/CircuitFlow.py
QuantumPathQSOAPySDK/circuit/flow/__init__.py
QuantumPathQSOAPySDK/circuit/gates/CircuitGates.py
QuantumPathQSOAPySDK/circuit/gates/__init__.py
QuantumPathQSOAPySDK/circuit/gates/basicGates.py
QuantumPathQSOAPySDK/circuit/gates/gates.py
QuantumPathQSOAPySDK/circuit/gates/measureGates.py
QuantumPathQSOAPySDK/circuit/gates/preparedGates.py
QuantumPathQSOAPySDK/circuit/gates/rotationGates.py
QuantumPathQSOAPySDK/circuit/gates/utilities.py
QuantumPathQSOAPySDK/objects/Application.py
QuantumPathQSOAPySDK/objects/Asset.py
QuantumPathQSOAPySDK/objects/AssetManagementData.py
QuantumPathQSOAPySDK/objects/AssetManagementResult.py
QuantumPathQSOAPySDK/objects/DeviceItem.py
QuantumPathQSOAPySDK/objects/Execution.py
QuantumPathQSOAPySDK/objects/FlowItem.py
QuantumPathQSOAPySDK/objects/QuantumExecutionHistoryEntry.py
QuantumPathQSOAPySDK/objects/SolutionItem.py
QuantumPathQSOAPySDK/objects/__init__.py
QuantumPathQSOAPySDK/qsoa/__init__.py
QuantumPathQSOAPySDK/qsoa/connectionPoints.py
QuantumPathQSOAPySDK/qsoa/dynamicConnectionPoints.py
QuantumPathQSOAPySDK/qsoa/securityConnectionPoints.py
QuantumPathQSOAPySDK/utils/Context.py
QuantumPathQSOAPySDK/utils/Exception.py
QuantumPathQSOAPySDK/utils/__init__.py
QuantumPathQSOAPySDK/utils/apiConnection.py
QuantumPathQSOAPySDK/utils/checker.py
QuantumPathQSOAPySDK-1.6.dist-info/METADATA
QuantumPathQSOAPySDK-1.6.dist-info/WHEEL
QuantumPathQSOAPySDK-1.6.dist-info/top_level.txt
QuantumPathQSOAPySDK-1.6.dist-info/RECORD
